dell_unisphere_mock_api/__init__.py
dell_unisphere_mock_api/__main__.py
dell_unisphere_mock_api/main.py
dell_unisphere_mock_api/version.py
dell_unisphere_mock_api/controllers/filesystem_controller.py
dell_unisphere_mock_api/controllers/job_controller.py
dell_unisphere_mock_api/controllers/lun_controller.py
dell_unisphere_mock_api/controllers/nas_server_controller.py
dell_unisphere_mock_api/controllers/pool_controller.py
dell_unisphere_mock_api/controllers/storage_resource_controller.py
dell_unisphere_mock_api/controllers/system_info.py
dell_unisphere_mock_api/core/auth.py
dell_unisphere_mock_api/core/config.py
dell_unisphere_mock_api/core/system_info.py
dell_unisphere_mock_api/models/disk.py
dell_unisphere_mock_api/models/disk_group.py
dell_unisphere_mock_api/models/filesystem.py
dell_unisphere_mock_api/models/host.py
dell_unisphere_mock_api/models/job.py
dell_unisphere_mock_api/models/lun.py
dell_unisphere_mock_api/models/nas_server.py
dell_unisphere_mock_api/models/pool.py
dell_unisphere_mock_api/models/pool_unit.py
dell_unisphere_mock_api/models/storage_resource.py
dell_unisphere_mock_api/routers/__init__.py
dell_unisphere_mock_api/routers/auth.py
dell_unisphere_mock_api/routers/disk.py
dell_unisphere_mock_api/routers/disk_group.py
dell_unisphere_mock_api/routers/filesystem.py
dell_unisphere_mock_api/routers/job.py
dell_unisphere_mock_api/routers/lun.py
dell_unisphere_mock_api/routers/nas_server.py
dell_unisphere_mock_api/routers/pool.py
dell_unisphere_mock_api/routers/pool_unit.py
dell_unisphere_mock_api/routers/storage_resource.py
dell_unisphere_mock_api/routers/system_info.py
dell_unisphere_mock_api/routers/user.py
dell_unisphere_mock_api/schemas/disk.py
dell_unisphere_mock_api/schemas/disk_group.py
dell_unisphere_mock_api/schemas/filesystem.py
dell_unisphere_mock_api/schemas/host.py
dell_unisphere_mock_api/schemas/job.py
dell_unisphere_mock_api/schemas/lun.py
dell_unisphere_mock_api/schemas/nas_server.py
dell_unisphere_mock_api/schemas/pool.py
dell_unisphere_mock_api-0.2.9.0.dist-info/METADATA
dell_unisphere_mock_api-0.2.9.0.dist-info/WHEEL
dell_unisphere_mock_api-0.2.9.0.dist-info/RECORD
