Metadata-Version: 2.4
Name: dell-unisphere-mock-api
Version: 0.2.9.0
Summary: A FastAPI-based mock implementation of the Dell EMC Unisphere REST API
Project-URL: Homepage, https://github.com/nirabo/dell-unisphere-mock-api
Project-URL: Bug Tracker, https://github.com/nirabo/dell-unisphere-mock-api/issues
Author-email: Lyuboslav Petrov <petrov.lyuboslav.work@gmail.com>
Classifier: Development Status :: 4 - Beta
Classifier: Framework :: FastAPI
Classifier: Intended Audience :: Developers
Classifier: License :: OSI Approved :: MIT License
Classifier: Operating System :: OS Independent
Classifier: Programming Language :: Python :: 3
Classifier: Programming Language :: Python :: 3.12
Classifier: Topic :: Software Development :: Testing
Requires-Python: >=3.10
Requires-Dist: fastapi>=0.104.1
Requires-Dist: passlib>=1.7.4
Requires-Dist: pydantic-settings>=2.1.0
Requires-Dist: pydantic>=2.5.2
Requires-Dist: python-jose[cryptography]>=3.3.0
Requires-Dist: python-multipart>=0.0.6
Requires-Dist: uvicorn>=0.24.0
Provides-Extra: dev
Requires-Dist: bandit>=1.7.6; extra == 'dev'
Requires-Dist: black>=23.12.0; extra == 'dev'
Requires-Dist: flake8-bugbear>=23.12.2; extra == 'dev'
Requires-Dist: flake8-docstrings>=1.7.0; extra == 'dev'
Requires-Dist: flake8-quotes>=3.3.2; extra == 'dev'
Requires-Dist: flake8>=6.1.0; extra == 'dev'
Requires-Dist: isort>=5.13.2; extra == 'dev'
Requires-Dist: mypy>=1.7.1; extra == 'dev'
Requires-Dist: pre-commit>=3.6.0; extra == 'dev'
Provides-Extra: test
Requires-Dist: httpx>=0.25.2; extra == 'test'
Requires-Dist: pytest-asyncio>=0.21.1; extra == 'test'
Requires-Dist: pytest-cov>=4.1.0; extra == 'test'
Requires-Dist: pytest>=7.4.3; extra == 'test'
